highresnet/__init__.py
highresnet/histogram.py
highresnet/inference.py
highresnet/preprocessing.py
highresnet/sampling.py
highresnet/cli/__init__.py
highresnet/cli/deepgif.py
highresnet/cli/download_oasis.py
highresnet/modules/__init__.py
highresnet/modules/convolution.py
highresnet/modules/dilation.py
highresnet/modules/highresnet.py
highresnet/modules/residual.py
highresnet-0.10.2.dist-info/AUTHORS.rst
highresnet-0.10.2.dist-info/LICENSE
highresnet-0.10.2.dist-info/METADATA
highresnet-0.10.2.dist-info/WHEEL
highresnet-0.10.2.dist-info/entry_points.txt
highresnet-0.10.2.dist-info/top_level.txt
highresnet-0.10.2.dist-info/RECORD
