Metadata-Version: 2.1
Name: highresnet
Version: 0.10.2
Summary: PyTorch implementation of HighRes3DNet
Home-page: https://github.com/fepegar/highresnet
Author: Fernando Perez-Garcia
Author-email: fernando.perezgarcia.17@ucl.ac.uk
License: MIT license
Keywords: highresnet
Platform: UNKNOWN
Classifier: Programming Language :: Python :: 3
Classifier: License :: OSI Approved :: MIT License
Classifier: Operating System :: OS Independent
Classifier: Intended Audience :: Science/Research
Classifier: Natural Language :: English
Classifier: Programming Language :: Python :: 3.5
Classifier: Programming Language :: Python :: 3.6
Classifier: Programming Language :: Python :: 3.7
Requires-Python: >=3.5
Requires-Dist: Click (>=7.0)
Requires-Dist: nibabel
Requires-Dist: numpy
Requires-Dist: SimpleITK
Requires-Dist: torch (>=1.1)
Requires-Dist: tqdm
